recipes/dev/lora_finetune_distributed_multi_dataset.py
recipes/dev/grpo_full_finetune_distributed.py
recipes/dev/generate_v2_distributed.py
recipes/dev/generate_v2.py
recipes/dev/early_exit_finetune_distributed.py
recipes/configs/qwen2_5/evaluation.yaml
recipes/configs/qwen2_5/7B_lora_single_device.yaml
recipes/configs/qwen2_5/7B_lora.yaml
recipes/configs/qwen2_5/7B_full_single_device.yaml
recipes/configs/qwen2_5/7B_full.yaml
recipes/configs/qwen2_5/72B_lora.yaml
recipes/configs/qwen2_5/3B_lora_single_device.yaml
recipes/configs/qwen2_5/3B_lora.yaml
recipes/configs/qwen2_5/3B_full_single_device.yaml
recipes/configs/qwen2_5/3B_full.yaml
recipes/configs/qwen2_5/32B_lora.yaml
recipes/configs/qwen2_5/14B_lora_single_device.yaml
recipes/configs/qwen2_5/1.5B_lora_single_device.yaml
recipes/configs/qwen2_5/1.5B_lora.yaml
recipes/configs/qwen2_5/1.5B_full_single_device.yaml
recipes/configs/qwen2_5/1.5B_full.yaml
recipes/configs/qwen2_5/0.5B_lora_single_device.yaml
recipes/configs/qwen2_5/0.5B_lora.yaml
recipes/configs/qwen2_5/0.5B_full_single_device.yaml
recipes/configs/qwen2_5/0.5B_full.yaml
recipes/configs/qwen2/evaluation.yaml
recipes/configs/qwen2/7B_lora_single_device.yaml
recipes/configs/qwen2/7B_lora.yaml
recipes/configs/qwen2/7B_full_single_device.yaml
recipes/configs/qwen2/7B_full.yaml
recipes/configs/qwen2/1.5_to_0.5B_KD_lora_single_device.yaml
recipes/configs/qwen2/1.5_to_0.5B_KD_lora_distributed.yaml
recipes/configs/qwen2/1.5B_lora_single_device.yaml
recipes/configs/qwen2/1.5B_lora.yaml
recipes/configs/qwen2/1.5B_full_single_device.yaml
recipes/configs/qwen2/1.5B_full.yaml
recipes/configs/qwen2/0.5B_lora_single_device.yaml
recipes/configs/qwen2/0.5B_lora.yaml
recipes/configs/qwen2/0.5B_full_single_device.yaml
recipes/configs/qwen2/0.5B_full.yaml
recipes/configs/phi4/evaluation.yaml
recipes/configs/phi4/14B_qlora_single_device.yaml
recipes/configs/phi4/14B_lora_single_device.yaml
recipes/configs/phi4/14B_lora.yaml
recipes/configs/phi4/14B_full_low_memory.yaml
torchtune-0.6.0.dist-info/METADATA
torchtune-0.6.0.dist-info/WHEEL
torchtune-0.6.0.dist-info/entry_points.txt
torchtune-0.6.0.dist-info/top_level.txt
torchtune-0.6.0.dist-info/RECORD
torchtune-0.6.0.dist-info/licenses/LICENSE
