Metadata-Version: 2.4
Name: torchtune
Version: 0.6.0
Summary: A native-PyTorch library for LLM fine-tuning
Author-email: PyTorch Team <packages@pytorch.org>
License: BSD 3-Clause License
Project-URL: GitHub, https://github.com/pytorch/torchtune
Project-URL: Documentation, https://pytorch.org/torchtune/main/index.html
Project-URL: Issues, https://github.com/pytorch/torchtune/issues
Keywords: pytorch,finetuning,llm
Requires-Python: >=3.9
License-File: LICENSE
Requires-Dist: torchdata==0.11.0
Requires-Dist: datasets
Requires-Dist: huggingface_hub[hf_transfer]
Requires-Dist: safetensors
Requires-Dist: kagglehub
Requires-Dist: sentencepiece
Requires-Dist: tiktoken
Requires-Dist: blobfile>=2
Requires-Dist: tokenizers
Requires-Dist: numpy
Requires-Dist: tqdm
Requires-Dist: omegaconf
Requires-Dist: psutil
Requires-Dist: Pillow>=9.4.0
Provides-Extra: dev
Requires-Dist: bitsandbytes>=0.43.0; extra == "dev"
Requires-Dist: comet_ml>=3.44.2; extra == "dev"
Requires-Dist: mlflow; extra == "dev"
Requires-Dist: pre-commit; extra == "dev"
Requires-Dist: pytest==7.4.0; extra == "dev"
Requires-Dist: pytest-cov; extra == "dev"
Requires-Dist: pytest-mock; extra == "dev"
Requires-Dist: pytest-integration; extra == "dev"
Requires-Dist: tensorboard; extra == "dev"
Requires-Dist: urllib3<2.0.0; extra == "dev"
Requires-Dist: wandb; extra == "dev"
Requires-Dist: expecttest; extra == "dev"
Dynamic: license-file
